simpleplots/__init__.py
simpleplots/__version__.py
simpleplots/base.py
simpleplots/dates.py
simpleplots/figure.py
simpleplots/themes.py
simpleplots/ticker.py
simpleplots/utils.py
simpleplots/visuals.py
simpleplots/fonts/arial.ttf
simpleplots-0.7.2.dist-info/LICENSE
simpleplots-0.7.2.dist-info/METADATA
simpleplots-0.7.2.dist-info/WHEEL
simpleplots-0.7.2.dist-info/top_level.txt
simpleplots-0.7.2.dist-info/RECORD
