Metadata-Version: 2.1
Name: simpleplots
Version: 0.7.2
Summary: "Pure Python, lightweight, Pillow-based plotting tool, focused on efficiency and prevention of memory losses."
Home-page: https://github.com/a-maliarov/simpleplots
Author: Anatolii Maliarov
Author-email: tly.mov@gmail.com
License: UNKNOWN
Project-URL: Source, https://github.com/a-maliarov/simpleplots
Platform: UNKNOWN
Classifier: Programming Language :: Python :: 3.7
Classifier: Programming Language :: Python :: 3.8
Classifier: Programming Language :: Python :: 3.9
Classifier: License :: OSI Approved :: MIT License
Classifier: Operating System :: OS Independent
Classifier: Development Status :: 5 - Production/Stable
Classifier: Natural Language :: English
Classifier: Intended Audience :: Developers
Classifier: Intended Audience :: Education
Classifier: Intended Audience :: Information Technology
License-File: LICENSE
Requires-Dist: pillow (<9.2.0,>=9.0.1)
Requires-Dist: numpy (>=1.21.5)
Requires-Dist: python-dateutil (>=2.8.2)
